.gitignore
CHANGES.txt
LICENSE.txt
MANIFEST.in
README.rst
requirements.txt
setup.py
tmpy/__init__.py
tmpy/corpus.py
tmpy/doc.py
tmpy/filters.py
tmpy/helper.py
tmpy/matrix.py
tmpy/reader.py
tmpy/source.py
tmpy/stopwords.py
tmpy/tokenizer.py
tmpy/transform.py
tmpy/weight.py
tmpy.egg-info/PKG-INFO
tmpy.egg-info/SOURCES.txt
tmpy.egg-info/dependency_links.txt
tmpy.egg-info/requires.txt
tmpy.egg-info/top_level.txt
tmpy/misc/texts/custom.xml
tmpy/misc/texts/loremipsum.txt
tmpy/misc/texts/rcv1_2330.xml
tmpy/misc/texts/reuters-21578.xml
tmpy/misc/texts/acq/reut-00001.xml
tmpy/misc/texts/acq/reut-00002.xml
tmpy/misc/texts/acq/reut-00003.xml
tmpy/misc/texts/acq/reut-00004.xml
tmpy/misc/texts/acq/reut-00005.xml
tmpy/misc/texts/acq/reut-00006.xml
tmpy/misc/texts/acq/reut-00007.xml
tmpy/misc/texts/acq/reut-00008.xml
tmpy/misc/texts/acq/reut-00009.xml
tmpy/misc/texts/acq/reut-00010.xml
tmpy/misc/texts/acq/reut-00011.xml
tmpy/misc/texts/acq/reut-00012.xml
tmpy/misc/texts/acq/reut-00013.xml
tmpy/misc/texts/acq/reut-00014.xml
tmpy/misc/texts/acq/reut-00015.xml
tmpy/misc/texts/acq/reut-00016.xml
tmpy/misc/texts/acq/reut-00017.xml
tmpy/misc/texts/acq/reut-00018.xml
tmpy/misc/texts/acq/reut-00020.xml
tmpy/misc/texts/acq/reut-00021.xml
tmpy/misc/texts/acq/reut-00022.xml
tmpy/misc/texts/acq/reut-00023.xml
tmpy/misc/texts/acq/reut-00024.xml
tmpy/misc/texts/acq/reut-00025.xml
tmpy/misc/texts/acq/reut-00026.xml
tmpy/misc/texts/acq/reut-00027.xml
tmpy/misc/texts/acq/reut-00028.xml
tmpy/misc/texts/acq/reut-00029.xml
tmpy/misc/texts/acq/reut-00030.xml
tmpy/misc/texts/acq/reut-00031.xml
tmpy/misc/texts/acq/reut-00032.xml
tmpy/misc/texts/acq/reut-00034.xml
tmpy/misc/texts/acq/reut-00035.xml
tmpy/misc/texts/acq/reut-00036.xml
tmpy/misc/texts/acq/reut-00039.xml
tmpy/misc/texts/acq/reut-00040.xml
tmpy/misc/texts/acq/reut-00042.xml
tmpy/misc/texts/acq/reut-00043.xml
tmpy/misc/texts/acq/reut-00045.xml
tmpy/misc/texts/acq/reut-00046.xml
tmpy/misc/texts/acq/reut-00047.xml
tmpy/misc/texts/acq/reut-00048.xml
tmpy/misc/texts/acq/reut-00049.xml
tmpy/misc/texts/acq/reut-00050.xml
tmpy/misc/texts/acq/reut-00051.xml
