Metadata-Version: 1.1
Name: tmpy
Version: 0.0.4
Summary: a text mining framework in Python
Home-page: https://github.com/fyears/tmpy
Author: Junwen Huang
Author-email: hjwdhjwd@gmail.com
License: BSD
Keywords: text mining
Platform: all
Classifier: Programming Language :: Python
Classifier: Development Status :: 4 - Beta
Classifier: Environment :: Other Environment
Classifier: Intended Audience :: Developers
Classifier: Intended Audience :: Science/Research
Classifier: License :: OSI Approved :: BSD License
Classifier: Operating System :: OS Independent
Classifier: Topic :: Scientific/Engineering :: Artificial Intelligence
Classifier: Topic :: Scientific/Engineering :: Information Analysis
Classifier: Topic :: Scientific/Engineering :: Mathematics
Classifier: Topic :: Text Processing :: General
Classifier: Topic :: Text Processing :: Linguistic
